ik_cli/__init__.py
ik_cli/__version__.py
ik_cli/cli.py
ik_cli/commands/__init__.py
ik_cli/commands/cmd_ip.py
ik_cli/commands/cmd_time.py
ik_cli/commands/constant.py
ik_cli/commands/exceptions.py
ik_cli/commands/models/__init__.py
ik_cli/commands/models/network.py
ik_cli-0.1.6.dist-info/METADATA
ik_cli-0.1.6.dist-info/WHEEL
ik_cli-0.1.6.dist-info/entry_points.txt
ik_cli-0.1.6.dist-info/top_level.txt
ik_cli-0.1.6.dist-info/RECORD
