Metadata-Version: 2.1
Name: ik-cli
Version: 0.1.6
Summary: My common cli tool.
Home-page: https://github.com/MerleLiuKun/ik-cli
Author: Ikaros Kun
Author-email: merle.liukun@gmail.com
License: MIT
Platform: UNKNOWN
Classifier: License :: OSI Approved :: MIT License
Classifier: Programming Language :: Python
Classifier: Programming Language :: Python :: 3
Classifier: Programming Language :: Python :: 3.6
Classifier: Programming Language :: Python :: 3.7
Classifier: Programming Language :: Python :: Implementation :: CPython
Classifier: Programming Language :: Python :: Implementation :: PyPy
Requires-Python: >=3.6.0
Requires-Dist: requests
Requires-Dist: click
